{"sentences": [{"word_features": [{"text": "itali\u00eb", "dep_length": 6, "super_sem_type": "concrete"}, {"text": ",", "punct_placement": "trailing"}, {"text": "officieel", "word_frequency": 4.85, "dep_length": 2}, {"text": "de"}, {"text": "italiaanse", "word_frequency": 4.69}, {"text": "republiek", "word_frequency": 4.71, "dep_length": 2, "super_sem_type": "abstract"}, {"text": ",", "punct_placement": "trailing"}, {"text": "is", "dep_length": 1}, {"text": "een"}, {"text": "land", "word_frequency": 5.69, "super_sem_type": "concrete"}, {"text": "in", "dep_length": 1}, {"text": "het"}, {"text": "zuiden", "word_frequency": 4.8, "dep_length": 2, "super_sem_type": "concrete"}, {"text": "van"}, {"text": "europa", "dep_length": 1, "super_sem_type": "concrete"}, {"text": ".", "punct_placement": "trailing"}], "score": 44.68576799999998, "level": 2, "mean_log_word_frequency": 4.948, "max_sdl": 6, "proportion_of_concrete_nouns": 0.8, "content_words_per_clause": 7.0}, {"word_features": [{"text": "itali\u00eb", "dep_length": 1, "super_sem_type": "concrete"}, {"text": "is"}, {"text": "onderdeel", "word_frequency": 5.15, "super_sem_type": "abstract"}, {"text": "van", "dep_length": 1}, {"text": "de"}, {"text": "europese", "dep_length": 2, "super_sem_type": "concrete"}, {"text": "unie", "super_sem_type": "abstract"}, {"text": "en", "dep_length": 1}, {"text": "is"}, {"text": "\u00e9\u00e9n", "dep_length": 6}, {"text": "van", "dep_length": 2}, {"text": "de", "dep_length": 1}, {"text": "zes"}, {"text": "landen", "word_frequency": 5.26, "dep_length": 3, "super_sem_type": "concrete"}, {"text": "die", "dep_length": 1}, {"text": "deze"}, {"text": "oprichtte", "word_frequency": 2.73, "dep_length": 2}, {"text": ".", "punct_placement": "trailing"}], "score": 39.49167999999999, "level": 2, "mean_log_word_frequency": 4.38, "max_sdl": 6, "proportion_of_concrete_nouns": 0.6, "content_words_per_clause": 2.0}, {"word_features": [{"text": "in"}, {"text": "itali\u00eb", "super_sem_type": "concrete"}, {"text": "betaalt", "word_frequency": 4.57}, {"text": "men"}, {"text": "met"}, {"text": "euro", "word_frequency": 5.25, "dep_length": 2, "super_sem_type": "concrete"}, {"text": "en"}, {"text": "spreekt", "word_frequency": 4.84, "dep_length": 4}, {"text": "men"}, {"text": "italiaans", "dep_length": 1, "super_sem_type": "abstract"}, {"text": ".", "punct_placement": "trailing"}], "score": 29.424186666666657, "level": 1, "mean_log_word_frequency": 4.886666666666667, "max_sdl": 4, "proportion_of_concrete_nouns": 0.6666666666666666, "content_words_per_clause": 2.5}, {"word_features": [{"text": "itali\u00eb", "super_sem_type": "concrete"}, {"text": "grenst", "word_frequency": 3.73}, {"text": "in", "dep_length": 1}, {"text": "het"}, {"text": "noorden", "word_frequency": 4.79, "dep_length": 2, "super_sem_type": "concrete"}, {"text": "aan"}, {"text": "zwitserland", "dep_length": 1, "super_sem_type": "concrete"}, {"text": "en"}, {"text": "oostenrijk", "dep_length": 3, "super_sem_type": "concrete"}, {"text": ",", "punct_placement": "trailing"}, {"text": "in", "dep_length": 1}, {"text": "het"}, {"text": "oosten", "word_frequency": 4.91, "dep_length": 9, "super_sem_type": "concrete"}, {"text": "aan"}, {"text": "sloveni\u00eb", "dep_length": 1, "super_sem_type": "concrete"}, {"text": "en", "dep_length": 2}, {"text": "in", "dep_length": 1}, {"text": "het"}, {"text": "westen", "word_frequency": 4.82, "dep_length": 15, "super_sem_type": "abstract"}, {"text": "aan"}, {"text": "frankrijk", "dep_length": 1, "super_sem_type": "concrete"}, {"text": ".", "punct_placement": "trailing"}], "score": 68.29499999999999, "level": 4, "mean_log_word_frequency": 4.5625, "max_sdl": 15, "proportion_of_concrete_nouns": 0.875, "content_words_per_clause": 9.0}, {"word_features": [{"text": "in"}, {"text": "itali\u00eb", "dep_length": 1, "super_sem_type": "concrete"}, {"text": "zelf", "word_frequency": 5.76}, {"text": "liggen", "word_frequency": 5.27}, {"text": "nog", "word_frequency": 6.53, "dep_length": 2}, {"text": "twee", "dep_length": 1}, {"text": "kleine", "word_frequency": 5.55}, {"text": "landjes", "word_frequency": 1.86, "dep_length": 3, "super_sem_type": "unknown"}, {"text": ",", "punct_placement": "trailing"}, {"text": "in", "dep_length": 1}, {"text": "het"}, {"text": "noorden", "word_frequency": 4.79, "dep_length": 6, "super_sem_type": "concrete"}, {"text": "het"}, {"text": "landje", "word_frequency": 3.36, "dep_length": 8, "super_sem_type": "unknown"}, {"text": "san", "super_sem_type": "unknown"}, {"text": "marino", "super_sem_type": "unknown"}, {"text": "en", "dep_length": 2}, {"text": "in", "dep_length": 1}, {"text": "de"}, {"text": "hoofdstad", "word_frequency": 5.68, "dep_length": 5, "super_sem_type": "concrete"}, {"text": "rome", "super_sem_type": "concrete"}, {"text": "ligt", "word_frequency": 5.53, "dep_length": 16}, {"text": "het"}, {"text": "landje", "word_frequency": 3.36, "dep_length": 1, "super_sem_type": "unknown"}, {"text": "vaticaanstad", "super_sem_type": "concrete"}, {"text": ".", "punct_placement": "trailing"}], "score": 55.41095399999999, "level": 3, "mean_log_word_frequency": 4.769, "max_sdl": 16, "proportion_of_concrete_nouns": 1.0, "content_words_per_clause": 6.5}, {"word_features": [{"text": "itali\u00eb", "dep_length": 6, "super_sem_type": "concrete"}, {"text": "is", "dep_length": 5}, {"text": "op", "dep_length": 1}, {"text": "de"}, {"text": "wereldkaart", "word_frequency": 5.03, "dep_length": 2, "super_sem_type": "concrete"}, {"text": "makkelijk", "word_frequency": 4.99, "dep_length": 1}, {"text": "te"}, {"text": "vinden", "word_frequency": 5.75}, {"text": "door", "dep_length": 1}, {"text": "haar"}, {"text": "vorm", "word_frequency": 5.22, "dep_length": 2, "super_sem_type": "undefined"}, {"text": ".", "punct_placement": "trailing"}], "score": 29.557834999999983, "level": 1, "mean_log_word_frequency": 5.2475000000000005, "max_sdl": 6, "proportion_of_concrete_nouns": 1.0, "content_words_per_clause": 5.0}, {"word_features": [{"text": "het"}, {"text": "land", "word_frequency": 5.69, "super_sem_type": "concrete"}, {"text": "lijkt", "word_frequency": 5.62}, {"text": "namelijk", "word_frequency": 4.94}, {"text": "op", "dep_length": 1}, {"text": "een"}, {"text": "laars", "word_frequency": 3.51, "dep_length": 3, "super_sem_type": "concrete"}, {"text": ".", "punct_placement": "trailing"}], "score": 23.62003999999999, "level": 1, "mean_log_word_frequency": 4.94, "max_sdl": 3, "proportion_of_concrete_nouns": 1.0, "content_words_per_clause": 3.0}, {"word_features": [{"text": "het"}, {"text": "vasteland", "word_frequency": 5.69, "dep_length": 9, "super_sem_type": "concrete"}, {"text": "van"}, {"text": "itali\u00eb", "dep_length": 1, "super_sem_type": "concrete"}, {"text": "wordt", "dep_length": 6}, {"text": "daarom", "word_frequency": 5.41, "dep_length": 5}, {"text": "wel", "word_frequency": 6.4, "dep_length": 4}, {"text": "de"}, {"text": "laars", "word_frequency": 3.51, "dep_length": 2, "super_sem_type": "concrete"}, {"text": "van"}, {"text": "itali\u00eb", "dep_length": 1, "super_sem_type": "concrete"}, {"text": "genoemd", "word_frequency": 5.17}, {"text": ".", "punct_placement": "trailing"}], "score": 33.598376, "level": 1, "mean_log_word_frequency": 5.236, "max_sdl": 9, "proportion_of_concrete_nouns": 1.0, "content_words_per_clause": 5.0}, {"word_features": [{"text": "daarnaast", "word_frequency": 5.06}, {"text": "behoren", "word_frequency": 4.51}, {"text": "nog", "word_frequency": 6.53}, {"text": "een", "dep_length": 1}, {"text": "groot", "word_frequency": 5.59}, {"text": "aantal", "word_frequency": 5.75, "dep_length": 3, "super_sem_type": "abstract"}, {"text": "eilanden", "word_frequency": 4.49, "super_sem_type": "concrete"}, {"text": "tot"}, {"text": "itali\u00eb", "dep_length": 2, "super_sem_type": "concrete"}, {"text": ",", "punct_placement": "trailing"}, {"text": "waarvan", "word_frequency": 5.17, "dep_length": 4}, {"text": "sicili\u00eb", "dep_length": 3, "super_sem_type": "concrete"}, {"text": "en"}, {"text": "sardini\u00eb", "dep_length": 1, "super_sem_type": "concrete"}, {"text": "de"}, {"text": "grootste", "word_frequency": 5.38, "dep_length": 5}, {"text": "zijn"}, {"text": ".", "punct_placement": "trailing"}], "score": 26.994259999999997, "level": 1, "mean_log_word_frequency": 5.31, "max_sdl": 5, "proportion_of_concrete_nouns": 0.8, "content_words_per_clause": 4.0}, {"word_features": [{"text": "het"}, {"text": "land", "word_frequency": 5.69, "dep_length": 2, "super_sem_type": "concrete"}, {"text": "wordt", "dep_length": 1}, {"text": "verder", "word_frequency": 5.66}, {"text": "omringd", "word_frequency": 4.1}, {"text": "door", "dep_length": 1}, {"text": "de"}, {"text": "middellandse", "dep_length": 2, "super_sem_type": "unknown"}, {"text": "zee", "super_sem_type": "concrete"}, {"text": ",", "punct_placement": "trailing"}, {"text": "de"}, {"text": "ionische", "dep_length": 5, "super_sem_type": "unknown"}, {"text": "zee", "super_sem_type": "concrete"}, {"text": ",", "punct_placement": "trailing"}, {"text": "de"}, {"text": "adriatische", "dep_length": 8, "super_sem_type": "unknown"}, {"text": "zee", "super_sem_type": "concrete"}, {"text": "en", "dep_length": 1}, {"text": "de"}, {"text": "ligurische", "dep_length": 12, "super_sem_type": "concrete"}, {"text": "zee", "super_sem_type": "concrete"}, {"text": ".", "punct_placement": "trailing"}], "score": 59.97289999999999, "level": 3, "mean_log_word_frequency": 5.15, "max_sdl": 12, "proportion_of_concrete_nouns": 1.0, "content_words_per_clause": 11.0}, {"word_features": [{"text": "in", "dep_length": 1}, {"text": "het"}, {"text": "midden", "word_frequency": 5.24, "dep_length": 7, "super_sem_type": "concrete"}, {"text": ",", "punct_placement": "trailing"}, {"text": "tussen", "dep_length": 1}, {"text": "het"}, {"text": "vasteland", "word_frequency": 5.69, "dep_length": 2, "super_sem_type": "concrete"}, {"text": "en", "dep_length": 2}, {"text": "de", "dep_length": 1}, {"text": "grote", "word_frequency": 5.85}, {"text": "eilanden", "word_frequency": 4.49, "dep_length": 6, "super_sem_type": "concrete"}, {"text": ",", "punct_placement": "trailing"}, {"text": "ligt", "word_frequency": 5.53}, {"text": "de"}, {"text": "tyrreense", "dep_length": 1, "super_sem_type": "unknown"}, {"text": "zee", "super_sem_type": "concrete"}, {"text": ".", "punct_placement": "trailing"}], "score": 36.07175999999998, "level": 2, "mean_log_word_frequency": 5.36, "max_sdl": 7, "proportion_of_concrete_nouns": 1.0, "content_words_per_clause": 7.0}, {"word_features": [{"text": "itali\u00eb", "super_sem_type": "concrete"}, {"text": "heeft", "word_frequency": 6.56}, {"text": "een", "dep_length": 1}, {"text": "lange", "word_frequency": 5.32}, {"text": "geschiedenis", "word_frequency": 5.24, "dep_length": 2, "super_sem_type": "abstract"}, {"text": ",", "punct_placement": "trailing"}, {"text": "die"}, {"text": "teruggaat", "word_frequency": 3.56, "dep_length": 1}, {"text": "tot", "dep_length": 2}, {"text": "in", "dep_length": 1}, {"text": "de"}, {"text": "oudheid", "word_frequency": 3.71, "dep_length": 3, "super_sem_type": "concrete"}, {"text": ".", "punct_placement": "trailing"}], "score": 30.040014666666664, "level": 1, "mean_log_word_frequency": 4.878, "max_sdl": 3, "proportion_of_concrete_nouns": 0.6666666666666666, "content_words_per_clause": 3.0}, {"word_features": [{"text": "vanuit", "dep_length": 1}, {"text": "de"}, {"text": "hoofdstad", "word_frequency": 5.68, "dep_length": 6, "super_sem_type": "concrete"}, {"text": "rome", "super_sem_type": "concrete"}, {"text": "is", "dep_length": 4}, {"text": "toen", "dep_length": 3}, {"text": "het"}, {"text": "romeinse", "dep_length": 1, "super_sem_type": "concrete"}, {"text": "rijk", "super_sem_type": "concrete"}, {"text": "ontstaan", "word_frequency": 4.97}, {"text": "dat", "dep_length": 12}, {"text": "op", "dep_length": 1}, {"text": "het"}, {"text": "hoogtepunt", "word_frequency": 4.33, "dep_length": 9, "super_sem_type": "undefined"}, {"text": "het", "dep_length": 1}, {"text": "hele", "word_frequency": 5.79}, {"text": "gebied", "word_frequency": 5.42, "dep_length": 6, "super_sem_type": "undefined"}, {"text": "rond", "dep_length": 1}, {"text": "de"}, {"text": "middellandse", "dep_length": 2, "super_sem_type": "unknown"}, {"text": "zee", "super_sem_type": "concrete"}, {"text": "in", "dep_length": 1}, {"text": "beslag", "word_frequency": 4.42, "super_sem_type": "undefined"}, {"text": "nam", "word_frequency": 5.15, "dep_length": 15}, {"text": ".", "punct_placement": "trailing"}], "score": 46.88630857142856, "level": 3, "mean_log_word_frequency": 5.1085714285714285, "max_sdl": 15, "proportion_of_concrete_nouns": 1.0, "content_words_per_clause": 6.0}, {"word_features": [{"text": "na", "dep_length": 1}, {"text": "de"}, {"text": "middeleeuwen", "word_frequency": 4.03, "dep_length": 6, "super_sem_type": "concrete"}, {"text": "is", "dep_length": 5}, {"text": "ook", "word_frequency": 6.69, "dep_length": 4}, {"text": "de"}, {"text": "renaissance", "dep_length": 2, "super_sem_type": "abstract"}, {"text": "in"}, {"text": "itali\u00eb", "dep_length": 1, "super_sem_type": "concrete"}, {"text": "ontstaan", "word_frequency": 4.97}, {"text": ".", "punct_placement": "trailing"}], "score": 31.73784666666664, "level": 1, "mean_log_word_frequency": 5.23, "max_sdl": 6, "proportion_of_concrete_nouns": 0.6666666666666666, "content_words_per_clause": 4.0}, {"word_features": [{"text": "het", "dep_length": 1}, {"text": "huidige", "word_frequency": 5.19}, {"text": "itali\u00eb", "super_sem_type": "concrete"}, {"text": "bestaat", "word_frequency": 5.37}, {"text": "nog", "word_frequency": 6.53}, {"text": "niet", "word_frequency": 6.96, "dep_length": 1}, {"text": "zo", "word_frequency": 6.43, "dep_length": 1}, {"text": "heel", "word_frequency": 6.0}, {"text": "lang", "word_frequency": 5.65, "dep_length": 4}, {"text": ",", "punct_placement": "trailing"}, {"text": "pas", "word_frequency": 5.45, "dep_length": 1}, {"text": "sinds"}, {"text": "1861", "dep_length": 7}, {"text": ".", "punct_placement": "trailing"}], "score": 19.549035000000003, "level": 1, "mean_log_word_frequency": 5.9475, "max_sdl": 7, "proportion_of_concrete_nouns": 1.0, "content_words_per_clause": 5.0}, {"word_features": [{"text": "hiervoor", "word_frequency": 4.78, "dep_length": 3}, {"text": "was", "dep_length": 2}, {"text": "het", "dep_length": 1}, {"text": "een"}, {"text": "verzameling", "word_frequency": 4.43, "super_sem_type": "abstract"}, {"text": "van", "dep_length": 1}, {"text": "allerlei"}, {"text": "landjes", "word_frequency": 1.86, "dep_length": 2, "super_sem_type": "unknown"}, {"text": ",", "punct_placement": "trailing"}, {"text": "net", "word_frequency": 5.86, "dep_length": 1}, {"text": "als"}, {"text": "duitsland", "dep_length": 5, "super_sem_type": "concrete"}, {"text": "toentertijd", "word_frequency": 3.2}, {"text": ".", "punct_placement": "embedded"}], "score": 49.066016, "level": 3, "mean_log_word_frequency": 4.026, "max_sdl": 5, "proportion_of_concrete_nouns": 0.5, "content_words_per_clause": 3.0}], "sentence_count": 16, "document_lint_score": 38.137121785714285, "document_difficulty_level": 2, "min_lint_score": 19.549035000000003, "max_lint_score": 68.29499999999999, "word_freq_compound_adjustment": true}